{
  "DataFile": "MD787_small_nissl/MD787-N427-2019.03.31-14.09.57_MD787_2_1280.png",
  "Type": "Float32",
  "Dimension": 3,
  "Endian": "big",
  "Sizes": [
    3,
    672,
    720,
    1
  ],
  "Space": "inferior-right-posterior",
  "SpaceDimension": 3,
  "SpaceUnits": [
    "um",
    "um",
    "um"
  ],
  "SpaceDirections": [
    "none",
    [
      44.160000000000004,
      0.0,
      0.0
    ],
    [
      0.0,
      44.160000000000004,
      0.0
    ],
    [
      0.0,
      0.0,
      200
    ]
  ],
  "SliceThickness": 10.0,
  "SpaceOrigin": [
    -14815.68,
    -15875.52,
    119900.0
  ]
}