{
  "DataFile": "MD787_small_nissl/MD787-N320-2019.03.30-19.36.23_MD787_3_0960.png",
  "Type": "Float32",
  "Dimension": 3,
  "Endian": "big",
  "Sizes": [
    3,
    712,
    960,
    1
  ],
  "Space": "inferior-right-posterior",
  "SpaceDimension": 3,
  "SpaceUnits": [
    "um",
    "um",
    "um"
  ],
  "SpaceDirections": [
    "none",
    [
      44.160000000000004,
      0.0,
      0.0
    ],
    [
      0.0,
      44.160000000000004,
      0.0
    ],
    [
      0.0,
      0.0,
      200
    ]
  ],
  "SliceThickness": 10.0,
  "SpaceOrigin": [
    -15698.880000000001,
    -21174.72,
    55900.0
  ]
}